sqllite3tools1/__init__.py
sqllite3tools1/__version__.py
sqllite3tools1/api_ref.py
sqllite3tools1-0.0.7.dist-info/LICENCE
sqllite3tools1-0.0.7.dist-info/METADATA
sqllite3tools1-0.0.7.dist-info/WHEEL
sqllite3tools1-0.0.7.dist-info/top_level.txt
sqllite3tools1-0.0.7.dist-info/RECORD
