Metadata-Version: 2.1
Name: sqllite3tools1
Version: 0.0.7
Summary: SQLITE tools
Home-page: UNKNOWN
Author: SanjarbekDev
Author-email: <sanjarbeksodiqov0302@gmail.com>
License: UNKNOWN
Keywords: execute,commit,fetchone,fetchall,create_table,info,select
Platform: UNKNOWN
Classifier: Development Status :: 1 - Planning
Classifier: Intended Audience :: Developers
Classifier: Programming Language :: Python :: 3
Classifier: Operating System :: Unix
Classifier: Operating System :: MacOS :: MacOS X
Classifier: Operating System :: Microsoft :: Windows
License-File: LICENCE
